waldorf/__init__.py
waldorf/cfg.py
waldorf/client.py
waldorf/common.py
waldorf/env.py
waldorf/master.py
waldorf/md_util.py
waldorf/slave.py
waldorf/threading_u.py
waldorf/util.py
waldorf/namespace/__init__.py
waldorf/namespace/client/__init__.py
waldorf/namespace/master/__init__.py
waldorf/namespace/master/admin.py
waldorf/namespace/master/client.py
waldorf/namespace/master/slave.py
waldorf/namespace/slave/__init__.py
waldorf/static/index.html
waldorf/static/css/darksalad.css
waldorf/static/fonts/UbuntuMonoBold.woff2
waldorf/static/fonts/UbuntuMonoNormal.woff2
waldorf/static/images/DarkSaladBackground_900x900.png
waldorf/static/images/arrow_down.png
waldorf/static/images/arrow_up.png
waldorf/static/images/favicon.ico
waldorf/static/js/jquery-3.3.1.min.js
waldorf/static/js/socket.io.slim.js
waldorf/static/js/sorttable.js
waldorf/static/js/waldorf.js
waldorf-0.6.0.post1.dist-info/LICENSE
waldorf-0.6.0.post1.dist-info/METADATA
waldorf-0.6.0.post1.dist-info/WHEEL
waldorf-0.6.0.post1.dist-info/top_level.txt
waldorf-0.6.0.post1.dist-info/RECORD
