Metadata-Version: 2.1
Name: waldorf
Version: 0.6.0.post1
Summary: Waldorf, a distribution computing package based on celery
Home-page: https://github.com/levelupai/waldorf.git
Author: SErAphLi, taibende
License: Apache
Platform: UNKNOWN
Classifier: Development Status :: 4 - Beta
Classifier: License :: OSI Approved :: Apache Software License
Classifier: Topic :: System :: Distributed Computing
Classifier: Topic :: Software Development :: Object Brokering
Classifier: Programming Language :: Python
Classifier: Programming Language :: Python :: 3
Classifier: Programming Language :: Python :: 3.5
Classifier: Programming Language :: Python :: 3.6
Classifier: Programming Language :: Python :: 3.7
Classifier: Programming Language :: Python :: Implementation :: CPython
Classifier: Programming Language :: Python :: Implementation :: PyPy
Classifier: Operating System :: POSIX :: Linux
Requires-Dist: virtualenv (>=16.5.0)
Requires-Dist: psutil (>=5.6.2)
Requires-Dist: aiohttp (==3.1.3)
Requires-Dist: celery (>=4.3.0)
Requires-Dist: python-socketio (>=4.0.1)
Requires-Dist: tqdm (>=4.23.3)
Requires-Dist: requests (>=2.21.0)
Requires-Dist: redis (>=3.2.1)
Requires-Dist: pycryptodome (>=3.8.1)
Requires-Dist: pexpect (>=4.7.0)
Requires-Dist: jsonpickle (>=1.1)
Requires-Dist: tabulate (>=0.8.3)
